LICENSE
MANIFEST.in
README.md
setup.py
django_hautomation.egg-info/PKG-INFO
django_hautomation.egg-info/SOURCES.txt
django_hautomation.egg-info/dependency_links.txt
django_hautomation.egg-info/requires.txt
django_hautomation.egg-info/top_level.txt
docs/harest_testing.txt
hacore/__init__.py
hacore/admin.py
hacore/models.py
harest/__init__.py
harest/auth.py
harest/forms.py
harest/middleware.py
harest/tests.py
harest/urls.py
harest/views_cmds.py
harest/views_device.py
harest/views_protocol.py
harest/templates/device/list.json