Metadata-Version: 1.1
Name: django-hautomation
Version: 2
Summary: A Django app which provides a REST API for home automation
Home-page: http://blog.digitalhigh.es
Author: Javier Pardo Blasco(jpardobl)
Author-email: jpardo@digitalhigh.es
License: BSD License
Platform: UNKNOWN
Classifier: Environment :: Web Environment
Classifier: Framework :: Django
Classifier: Intended Audience :: Developers
Classifier: License :: OSI Approved :: BSD License
Classifier: Operating System :: OS Independent
Classifier: Programming Language :: Python
Classifier: Programming Language :: Python :: 2.6
Classifier: Programming Language :: Python :: 2.7
Classifier: Topic :: Internet :: WWW/HTTP
Classifier: Topic :: Internet :: WWW/HTTP :: Dynamic Content
Classifier: Topic :: Home Automation
